viu_sitemap_parser-0.2.8.dist-info/licenses/LICENSE
viusitemapparser/__init__.py
viusitemapparser/detect_filetype.py
viusitemapparser/get_file.py
viusitemapparser/get_sitemap_entries.py
viusitemapparser/parse_file.py
viusitemapparser/sitemap_file.py
viusitemapparser/url_functions.py
viusitemapparser/vsp.py
viu_sitemap_parser-0.2.8.dist-info/METADATA
viu_sitemap_parser-0.2.8.dist-info/WHEEL
viu_sitemap_parser-0.2.8.dist-info/top_level.txt
viu_sitemap_parser-0.2.8.dist-info/RECORD
