Metadata-Version: 2.4
Name: viu_sitemap_parser
Version: 0.2.8
License: MIT
License-File: LICENSE
Dynamic: description
Dynamic: description-content-type
Dynamic: license
Dynamic: license-file
